brk_client/__init__.py
brk_client-0.1.0a3.dist-info/METADATA
brk_client-0.1.0a3.dist-info/WHEEL
brk_client-0.1.0a3.dist-info/RECORD
