Metadata-Version: 2.4
Name: brk-client
Version: 0.1.0a3
Summary: Python client for the Bitcoin Research Kit
Project-URL: Homepage, https://bitcoinresearchkit.org
Project-URL: Repository, https://github.com/bitcoinresearchkit/brk
License-Expression: MIT
Keywords: analytics,bitcoin,blockchain,on-chain
Classifier: Development Status :: 3 - Alpha
Classifier: Intended Audience :: Developers
Classifier: License :: OSI Approved :: MIT License
Classifier: Programming Language :: Python :: 3
Classifier: Programming Language :: Python :: 3.11
Classifier: Programming Language :: Python :: 3.12
Classifier: Programming Language :: Python :: 3.13
Classifier: Typing :: Typed
Requires-Python: >=3.11
